{
    "users": [{
        "id": "1",
        "name": "Dilan Sudarshana",
        "dob": "03 12 2025",
        "gender": "male",
        "email": "d@gmail.com",
        "password": 123
    }],
    "posts": [{
            "id": 1,
            "user_name": "Dilan Sudarshana",
            "date": "2025-03-04 12:00:00",
            "like_count": 25,
            "comment_count": 5,
            "shair_count": 2,
            "image": "https://img.freepik.com/free-photo/still-life-with-indoor-plants_23-2151024966.jpg?t=st=1740555982~exp=1740559582~hmac=be2d4f5d4aad89aaef3e710145744a7e7f37659dfa619ade374c4e5e2fb1cc49&w=740"
        },
        {
            "id": 1,
            "user_name": "Dilan Sudarshana",
            "date": "2025-03-04 12:00:00",
            "like_count": 25,
            "comment_count": 5,
            "shair_count": 2,
            "image": "https://img.freepik.com/free-photo/still-life-with-indoor-plants_23-2151024966.jpg?t=st=1740555982~exp=1740559582~hmac=be2d4f5d4aad89aaef3e710145744a7e7f37659dfa619ade374c4e5e2fb1cc49&w=740"
        },
        {
            "id": 1,
            "user_name": "Dilan Sudarshana",
            "date": "2025-03-04 12:00:00",
            "like_count": 25,
            "comment_count": 5,
            "shair_count": 2,
            "image": "https://img.freepik.com/free-photo/still-life-with-indoor-plants_23-2151024966.jpg?t=st=1740555982~exp=1740559582~hmac=be2d4f5d4aad89aaef3e710145744a7e7f37659dfa619ade374c4e5e2fb1cc49&w=740"
        },
        {
            "id": 1,
            "user_name": "Dilan Sudarshana",
            "date": "2025-03-04 12:00:00",
            "like_count": 25,
            "comment_count": 5,
            "shair_count": 2,
            "image": "https://img.freepik.com/free-photo/still-life-with-indoor-plants_23-2151024966.jpg?t=st=1740555982~exp=1740559582~hmac=be2d4f5d4aad89aaef3e710145744a7e7f37659dfa619ade374c4e5e2fb1cc49&w=740"
        }
    ]
}